aidial_sdk/__init__.py
aidial_sdk/_errors.py
aidial_sdk/_pydantic/__init__.py
aidial_sdk/_pydantic/_compat.py
aidial_sdk/_pydantic/_model_config.py
aidial_sdk/application.py
aidial_sdk/chat_completion/__init__.py
aidial_sdk/chat_completion/_types.py
aidial_sdk/chat_completion/base.py
aidial_sdk/chat_completion/choice.py
aidial_sdk/chat_completion/choice_base.py
aidial_sdk/chat_completion/chunks.py
aidial_sdk/chat_completion/enums.py
aidial_sdk/chat_completion/form.py
aidial_sdk/chat_completion/function_call.py
aidial_sdk/chat_completion/function_tool_call.py
aidial_sdk/chat_completion/request.py
aidial_sdk/chat_completion/response.py
aidial_sdk/chat_completion/stage.py
aidial_sdk/deployment/__init__.py
aidial_sdk/deployment/configuration.py
aidial_sdk/deployment/from_request_mixin.py
aidial_sdk/deployment/rate.py
aidial_sdk/deployment/tokenize.py
aidial_sdk/deployment/truncate_prompt.py
aidial_sdk/embeddings/__init__.py
aidial_sdk/embeddings/base.py
aidial_sdk/embeddings/request.py
aidial_sdk/embeddings/response.py
aidial_sdk/exceptions.py
aidial_sdk/header_propagator.py
aidial_sdk/pydantic/v2.py
aidial_sdk/pydantic_v1/__init__.py
aidial_sdk/telemetry/__init__.py
aidial_sdk/telemetry/init.py
aidial_sdk/telemetry/types.py
aidial_sdk/utils/__init__.py
aidial_sdk/utils/_attachment.py
aidial_sdk/utils/_cancel_scope.py
aidial_sdk/utils/_content_stream.py
aidial_sdk/utils/_indexed_list.py
aidial_sdk/utils/_reflection.py
aidial_sdk/utils/env.py
aidial_sdk/utils/errors.py
aidial_sdk/utils/json.py
aidial_sdk/utils/log_config.py
aidial_sdk/utils/logging.py
aidial_sdk/utils/merge_chunks.py
aidial_sdk/utils/pydantic.py
aidial_sdk/utils/streaming.py
aidial_sdk-0.28.0.dist-info/LICENSE
aidial_sdk-0.28.0.dist-info/METADATA
aidial_sdk-0.28.0.dist-info/WHEEL
aidial_sdk-0.28.0.dist-info/RECORD
