Metadata-Version: 2.3
Name: aidial-sdk
Version: 0.28.0
Summary: Framework to create applications and model adapters for AI DIAL
License: Apache-2.0
Author: EPAM RAIL
Author-email: SpecialEPM-DIALDevTeam@epam.com
Requires-Python: >=3.9,<4.0
Classifier: License :: OSI Approved :: Apache Software License
Classifier: Programming Language :: Python :: 3
Classifier: Programming Language :: Python :: 3.9
Classifier: Programming Language :: Python :: 3.10
Classifier: Programming Language :: Python :: 3.11
Classifier: Programming Language :: Python :: 3.12
Classifier: Programming Language :: Python :: 3.13
Provides-Extra: httpx
Provides-Extra: telemetry
Requires-Dist: fastapi (>=0.51,<1.0)
Requires-Dist: httpx (>=0.25.0,<1) ; extra == "httpx"
Requires-Dist: opentelemetry-api (>=1.22.0,<2.0) ; extra == "telemetry"
Requires-Dist: opentelemetry-exporter-otlp-proto-grpc (>=1.22.0,<2.0) ; extra == "telemetry"
Requires-Dist: opentelemetry-exporter-prometheus (>=0.43b0) ; extra == "telemetry"
Requires-Dist: opentelemetry-instrumentation-aiohttp-client (>=0.43b0) ; extra == "telemetry"
Requires-Dist: opentelemetry-instrumentation-fastapi (>=0.43b0) ; extra == "telemetry"
Requires-Dist: opentelemetry-instrumentation-httpx (>=0.43b0) ; extra == "telemetry"
Requires-Dist: opentelemetry-instrumentation-logging (>=0.43b0) ; extra == "telemetry"
Requires-Dist: opentelemetry-instrumentation-requests (>=0.43b0) ; extra == "telemetry"
Requires-Dist: opentelemetry-instrumentation-system-metrics (>=0.43b0) ; extra == "telemetry"
Requires-Dist: opentelemetry-instrumentation-urllib (>=0.43b0) ; extra == "telemetry"
Requires-Dist: opentelemetry-sdk (>=1.22.0,<2.0) ; extra == "telemetry"
Requires-Dist: prometheus-client (>=0.17.1,<=0.21) ; extra == "telemetry"
Requires-Dist: pydantic (>=1.10.17,<3)
Requires-Dist: uvicorn (>=0.19,<1.0)
Requires-Dist: wrapt (>=1.10,<2)
Project-URL: Documentation, https://epam-rail.com/dial_api
Project-URL: Homepage, https://epam-rail.com
Project-URL: Repository, https://github.com/epam/ai-dial-sdk
